amrendras/__init__.py
amrendras/amrendras.py
amrendras-1.0.1.dist-info/METADATA
amrendras-1.0.1.dist-info/WHEEL
amrendras-1.0.1.dist-info/top_level.txt
amrendras-1.0.1.dist-info/RECORD
