Metadata-Version: 2.1
Name: amrendras
Version: 1.0.1
Summary: maja le liya
Author: Prajwal
Author-email: <prajwalupadhyay13@gmail.com>
Keywords: python,video,stream,video stream,camera stream,sockets
Classifier: Development Status :: 1 - Planning
Classifier: Intended Audience :: Developers
Classifier: Programming Language :: Python :: 3
Classifier: Operating System :: Unix
Classifier: Operating System :: MacOS :: MacOS X
Classifier: Operating System :: Microsoft :: Windows
